sigma/backends/stix/__init__.py
sigma/backends/stix/stix.py
sigma/pipelines/stix/__init__.py
sigma/pipelines/stix/stix.py
pysigma_backend_stix-0.1.8.dist-info/LICENSE
pysigma_backend_stix-0.1.8.dist-info/METADATA
pysigma_backend_stix-0.1.8.dist-info/WHEEL
pysigma_backend_stix-0.1.8.dist-info/RECORD
